{"tabela":"QK6","nome":"Itens FMEA de Projeto","nome_eng":"Project FMEA Items","modo":"C","arquivo":"QK6990","campos":[{"campo":"QK6_FILIAL","titulo":"Filial","tipo":"C","tam":2,"dec":0},{"campo":"QK6_PECA","titulo":"No. da Peca","tipo":"C","tam":40,"dec":0},{"campo":"QK6_REV","titulo":"Revisao","tipo":"C","tam":2,"dec":0},{"campo":"QK6_REVINV","titulo":"Rev Invertid","tipo":"C","tam":2,"dec":0},{"campo":"QK6_ITEM","titulo":"Item","tipo":"C","tam":5,"dec":0},{"campo":"QK6_ENTER1","titulo":"Funcao","tipo":"C","tam":11,"dec":0,"ini_padrao":"\"<< Enter >>\""},{"campo":"QK6_ENTER2","titulo":"Modo Falha","tipo":"C","tam":11,"dec":0,"ini_padrao":"\"<< Enter >>\""},{"campo":"QK6_ENTER3","titulo":"Efeito Falha","tipo":"C","tam":11,"dec":0,"ini_padrao":"\"<< Enter >>\""},{"campo":"QK6_SEVER","titulo":"Severidade","tipo":"C","tam":2,"dec":0,"validacao":"Pertence(\"  1 2 3 4 5 6 7 8 9 10\")"},{"campo":"QK6_CLASS","titulo":"Classific.","tipo":"C","tam":2,"dec":0},{"campo":"QK6_ENTER4","titulo":"Causa Falha","tipo":"C","tam":11,"dec":0,"ini_padrao":"\"<< Enter >>\""},{"campo":"QK6_OCORR","titulo":"Ocorrencia","tipo":"C","tam":2,"dec":0,"validacao":"Pertence(\"  1 2 3 4 5 6 7 8 9 10\")"},{"campo":"QK6_ENTER5","titulo":"Controles","tipo":"C","tam":11,"dec":0,"ini_padrao":"\"<< Enter >>\""},{"campo":"QK6_DETEC","titulo":"Deteccao","tipo":"C","tam":2,"dec":0,"validacao":"Pertence(\"  1 2 3 4 5 6 7 8 9 10\")"},{"campo":"QK6_NPR","titulo":"NPR","tipo":"C","tam":4,"dec":0},{"campo":"QK6_ENTER6","titulo":"Acoes Recome","tipo":"C","tam":11,"dec":0,"ini_padrao":"\"<< Enter >>\""},{"campo":"QK6_RESP","titulo":"Responsavel","tipo":"C","tam":30,"dec":0},{"campo":"QK6_PRAZO","titulo":"Prazo","tipo":"D","tam":8,"dec":0},{"campo":"QK6_ENTER7","titulo":"Acoes Tomada","tipo":"C","tam":11,"dec":0,"ini_padrao":"\"<< Enter >>\""},{"campo":"QK6_RSEVER","titulo":"Sever Res Ac","tipo":"C","tam":2,"dec":0,"validacao":"Pertence(\"  1 2 3 4 5 6 7 8 9 10\")"},{"campo":"QK6_ROCORR","titulo":"Ocorr Res Ac","tipo":"C","tam":2,"dec":0,"validacao":"Pertence(\"  1 2 3 4 5 6 7 8 9 10\")"},{"campo":"QK6_RDETEC","titulo":"Detec Res Ac","tipo":"C","tam":2,"dec":0,"validacao":"Pertence(\"  1 2 3 4 5 6 7 8 9 10\")"},{"campo":"QK6_RNPR","titulo":"NPR Res Ac","tipo":"C","tam":4,"dec":0},{"campo":"QK6_CHAVE1","titulo":"Cod.Lig.IFun","tipo":"C","tam":8,"dec":0},{"campo":"QK6_CHAVE2","titulo":"Cod.Lig.MFP","tipo":"C","tam":8,"dec":0},{"campo":"QK6_CHAVE3","titulo":"Cod.Lig.EPF","tipo":"C","tam":8,"dec":0},{"campo":"QK6_CHAVE4","titulo":"Cod.Lig.CMF","tipo":"C","tam":8,"dec":0},{"campo":"QK6_CHAVE5","titulo":"Cod.Lig.CPrj","tipo":"C","tam":8,"dec":0},{"campo":"QK6_CHAVE6","titulo":"Cod.Lig.AR","tipo":"C","tam":8,"dec":0},{"campo":"QK6_CHAVE7","titulo":"Cod.Lig.AT","tipo":"C","tam":8,"dec":0},{"campo":"QK6_SEQ","titulo":"Sequencia","tipo":"C","tam":5,"dec":0},{"campo":"QK6_CODRES","titulo":"Cod. Respons","tipo":"C","tam":27,"dec":0,"validacao":"QA_CHKMAT(CFILANT,M->QK6_CODRES) .or. Vazio()"},{"campo":"QK6_FILRES","titulo":"Filial Resp.","tipo":"C","tam":2,"dec":0},{"campo":"QK6_DATEEF","titulo":"Data Efetiva","tipo":"D","tam":8,"dec":0}],"indices":[{"ordem":"1","chave":"QK6_FILIAL+QK6_PECA+QK6_REV+QK6_ITEM","descricao":"No. da Peca + Revisao + Item"},{"ordem":"2","chave":"QK6_FILIAL+QK6_PECA+QK6_REVINV+QK6_ITEM","descricao":"No. da Peca + Rev Invertid + Item"},{"ordem":"3","chave":"QK6_FILIAL+QK6_CHAVE1","descricao":"Cod.Lig.IFun"},{"ordem":"4","chave":"QK6_FILIAL+QK6_PECA+QK6_REV+QK6_SEQ","descricao":"No. da Peca + Revisao + Sequencia"}]}