{"tabela":"V9Y","nome":"Observações","nome_eng":"Notes","modo":"E","arquivo":"V9Y990","campos":[{"campo":"V9Y_FILIAL","titulo":"Filial","tipo":"C","tam":2,"dec":0},{"campo":"V9Y_ID","titulo":"ID","tipo":"C","tam":6,"dec":0,"validacao":"GetSx8Num(\"V9Y\",\"V9YID\")"},{"campo":"V9Y_VERSAO","titulo":"Id Ver Reg","tipo":"C","tam":14,"dec":0},{"campo":"V9Y_NRPROC","titulo":"Nr Proc","tipo":"C","tam":20,"dec":0},{"campo":"V9Y_CPFTRA","titulo":"CPF","tipo":"C","tam":11,"dec":0},{"campo":"V9Y_MATRIC","titulo":"Matricula","tipo":"C","tam":30,"dec":0},{"campo":"V9Y_CODCAT","titulo":"Cod Categ","tipo":"C","tam":6,"dec":0,"validacao":"xFunVldCmp(\"C87\",,,,2,.F.)"},{"campo":"V9Y_DTINIC","titulo":"Data Inicio","tipo":"D","tam":8,"dec":0},{"campo":"V9Y_DTREMU","titulo":"Data Remun","tipo":"D","tam":8,"dec":0},{"campo":"V9Y_VRSAL","titulo":"Vlr Remunera","tipo":"N","tam":14,"dec":2},{"campo":"V9Y_UNDSAL","titulo":"Und. Salário","tipo":"C","tam":1,"dec":0,"combo":"1= Por hora;2=Por dia;3=Por semana;4=Por quinzena;5=Por mês;6=Por tarefa;7= Não aplicável - Salário exclusivamente variável"},{"campo":"V9Y_DSCSAL","titulo":"Desc Salario","tipo":"M","tam":999,"dec":0}],"indices":[{"ordem":"1","chave":"V9Y_FILIAL+V9Y_ID+V9Y_VERSAO+V9Y_NRPROC+V9Y_CPFTRA+V9Y_MATRIC+V9Y_CODCAT+DTOS(V9Y_DTINIC)+DTOS(V9Y_DTREMU)","descricao":"ID + Id Ver Reg + Nr Proc + CPF + Matricula + Cod Categ + Data Inicio"}]}