{"tabela":"T20","nome":"Outras Movimentações Internas","nome_eng":"Other Internal Movement","modo":"E","arquivo":"T20990","campos":[{"campo":"T20_FILIAL","titulo":"Filial","tipo":"C","tam":2,"dec":0},{"campo":"T20_ID","titulo":"ID","tipo":"C","tam":36,"dec":0},{"campo":"T20_DTMOV","titulo":"Dt. Moviment","tipo":"D","tam":8,"dec":0},{"campo":"T20_CODITO","titulo":"ID. Item Ori","tipo":"C","tam":36,"dec":0,"validacao":"XFUNVLDCMP(\"C1L\",3)"},{"campo":"T20_ITORIG","titulo":"Item Origem","tipo":"C","tam":60,"dec":0,"validacao":"XFUNVldCmp(\"C1L\",1)","ini_padrao":"IF(!INCLUI.AND.!EMPTY(T20->T20_CODITO),POSICIONE(\"C1L\",3,XFILIAL(\"C1L\")+T20->T20_CODITO,\"C1L_CODIGO\"),\"\")"},{"campo":"T20_DESITO","titulo":"Descri. Item","tipo":"C","tam":220,"dec":0,"ini_padrao":"If(!INCLUI,Posicione(\"C1L\",3,xFilial(\"C1L\") + T20->T20_CODITO, \"Alltrim(C1L_CODIGO)+' - '+C1L_DESCRI\"), \"\")"},{"campo":"T20_CODITD","titulo":"ID. Item Des","tipo":"C","tam":36,"dec":0,"validacao":"XFUNVLDCMP(\"C1L\",3)"},{"campo":"T20_ITDEST","titulo":"Item Destino","tipo":"C","tam":60,"dec":0,"validacao":"XFUNVldCmp(\"C1L\",1)","ini_padrao":"IF(!INCLUI.AND.!EMPTY(T20->T20_CODITD),POSICIONE(\"C1L\",3,XFILIAL(\"C1L\")+T20->T20_CODITD,\"C1L_CODIGO\"),\"\")"},{"campo":"T20_DESITD","titulo":"Descri. Item","tipo":"C","tam":220,"dec":0,"ini_padrao":"If(!INCLUI,Posicione(\"C1L\",3,xFilial(\"C1L\") + T20->T20_CODITD, \"Alltrim(C1L_CODIGO)+' - '+C1L_DESCRI\"), \"\")"},{"campo":"T20_QTDMOV","titulo":"Qtd.Mov. Ori","tipo":"N","tam":16,"dec":3},{"campo":"T20_QTDMDE","titulo":"Qtd.Mov.Dest","tipo":"N","tam":16,"dec":3}],"indices":[{"ordem":"1","chave":"T20_FILIAL+T20_ID+DTOS(T20_DTMOV)+T20_CODITO+T20_CODITD","descricao":"ID + Dt. Moviment + ID. Item Ori + ID. Item Des"}],"gatilhos":[{"origem":"T20_CODITD","tipo":"X","seq":"001","destino":"","regra":"C1L->(Alltrim(C1L_CODIGO)+' - '+Alltrim(C1L_DESCRI))"},{"origem":"T20_CODITO","tipo":"X","seq":"001","destino":"","regra":"C1L->(Alltrim(C1L_CODIGO)+' - '+Alltrim(C1L_DESCRI))"},{"origem":"T20_ITDEST","tipo":"X","seq":"001","destino":"","regra":"C1L->(Alltrim(C1L_ID))"},{"origem":"T20_ITDEST","tipo":"P","seq":"002","destino":"","regra":"C1L->(ALLTRIM(C1L_CODIGO)+' - '+SubStr(C1L_DESCRI,1,150))"},{"origem":"T20_ITORIG","tipo":"X","seq":"001","destino":"","regra":"C1L->(Alltrim(C1L_ID))"},{"origem":"T20_ITORIG","tipo":"P","seq":"002","destino":"","regra":"C1L->(ALLTRIM(C1L_CODIGO)+' - '+SubStr(C1L_DESCRI,1,150))"}]}