{"tabela":"TWD","nome":"Itens do Checklist","nome_eng":"Checklist items","modo":"E","arquivo":"TWD990","campos":[{"campo":"TWD_FILIAL","titulo":"Filial","tipo":"C","tam":2,"dec":0},{"campo":"TWD_CODTWC","titulo":"CódChecklist","tipo":"C","tam":6,"dec":0,"validacao":"Vazio() .or. ExistCpo(\"TWC\")"},{"campo":"TWD_ITEM","titulo":"Item","tipo":"C","tam":3,"dec":0},{"campo":"TWD_TIPO","titulo":"Tipo","tipo":"C","tam":1,"dec":0,"validacao":"Pertence(\"123\")","ini_padrao":"\"3\"","combo":"1=Saída;2=Retorno;3=Ambos"},{"campo":"TWD_DESCIT","titulo":"Descrição","tipo":"C","tam":40,"dec":0},{"campo":"TWD_PRINT","titulo":"Impr.ChkLst?","tipo":"C","tam":1,"dec":0,"validacao":"Pertence(\"12\")","ini_padrao":"\"1\"","combo":"1=Sim;2=Não"},{"campo":"TWD_COMEXE","titulo":"Ação(Marcar)","tipo":"C","tam":20,"dec":0},{"campo":"TWD_COMDES","titulo":"Ação (Desm.)","tipo":"C","tam":20,"dec":0}],"indices":[{"ordem":"1","chave":"TWD_FILIAL+TWD_CODTWC+TWD_ITEM","descricao":"CódChecklist + Item"},{"ordem":"2","chave":"TWD_FILIAL+TWD_CODTWC+TWD_TIPO","descricao":"CódChecklist + Tipo"},{"ordem":"3","chave":"TWD_FILIAL+TWD_CODTWC+TWD_PRINT","descricao":"CódChecklist + Impr.ChkLst?"},{"ordem":"4","chave":"TWD_FILIAL+TWD_CODTWC+TWD_DESCIT","descricao":"CódChecklist + Descrição"}],"relacionamentos":[{"dominio":"TWD","expressao_dom":"TWD_CODTWC+TWD_ITEM","identificador":"001","expressao_ident":""}]}