{"tabela":"C6M","nome":"Crédito Pres Estoque Abertura","nome_eng":"Opening Stock Pres Credit","modo":"E","arquivo":"C6M990","campos":[{"campo":"C6M_FILIAL","titulo":"Filial","tipo":"C","tam":2,"dec":0},{"campo":"C6M_ID","titulo":"ID","tipo":"C","tam":6,"dec":0,"ini_padrao":"GetSx8Num(\"C6M\",\"C6M_ID\")"},{"campo":"C6M_PERIOD","titulo":"Data Movto","tipo":"D","tam":8,"dec":0,"validacao":"XFUNVldUni(\"C6M\",1,DTOS(M->C6M_PERIOD)+FWFLDGET(\"C6M_NATOPE\"))"},{"campo":"C6M_NATOPE","titulo":"Nat.Oper.","tipo":"C","tam":6,"dec":0,"validacao":"XFUNVldCmp(\"C11\",3) .And. XFUNVldUni(\"C6M\",1,DTOS(FWFLDGET(\"C6M_PERIOD\"))+M->C6M_NATOPE)"},{"campo":"C6M_DNATOP","titulo":"D.Nat.Op.","tipo":"C","tam":100,"dec":0,"ini_padrao":"IF(!INCLUI .AND. !EMPTY(C6M->C6M_NATOPE),POSICIONE(\"C11\",3,xFilial(\"C11\")+C6M->C6M_NATOPE, \"C11_CODIGO+' - '+C11_DESCRI\"),\"\")"},{"campo":"C6M_TOTEST","titulo":"Vl. Tot. Est","tipo":"N","tam":16,"dec":2},{"campo":"C6M_ESTIMP","titulo":"Vl. Est. Imp","tipo":"N","tam":16,"dec":2},{"campo":"C6M_VBCEST","titulo":"Vl.Base Est.","tipo":"N","tam":16,"dec":2,"validacao":"XFUNVldVal()"},{"campo":"C6M_VBCMES","titulo":"Vl.Bc Mensal","tipo":"N","tam":16,"dec":2,"validacao":"XFUNVldVal()"},{"campo":"C6M_CSTPIS","titulo":"Cod.CST.PIS","tipo":"C","tam":6,"dec":0,"validacao":"XFUNVldCmp(\"C17\",3)"},{"campo":"C6M_DCSTPI","titulo":"Desc CST PIS","tipo":"C","tam":220,"dec":0,"ini_padrao":"IF(!INCLUI.AND.!EMPTY(C6M->C6M_CSTPIS),POSICIONE(\"C17\",3,xFilial(\"C17\")+C6M->C6M_CSTPIS,\"C17_CODIGO+' - '+C17_DESCRI\"),\"\")"},{"campo":"C6M_ALQPIS","titulo":"Aliq. PIS","tipo":"N","tam":8,"dec":4},{"campo":"C6M_CRDPIS","titulo":"Vl.Crd. PIS","tipo":"N","tam":16,"dec":2,"validacao":"XFUNVldVal()"},{"campo":"C6M_CSTCOF","titulo":"Cod CST COF","tipo":"C","tam":6,"dec":0,"validacao":"XFUNVldCmp(\"C17\",3)"},{"campo":"C6M_DCSTCO","titulo":"D.CST Cofins","tipo":"C","tam":220,"dec":0,"ini_padrao":"IF(!INCLUI.AND.!EMPTY(C6M->C6M_CSTCOF),POSICIONE(\"C17\",3,xFilial(\"C17\")+C6M->C6M_CSTCOF,\"C17_CODIGO+' - '+C17_DESCRI\"),\"\")"},{"campo":"C6M_ALQCOF","titulo":"Aliq Cofins","tipo":"N","tam":8,"dec":4},{"campo":"C6M_CRDCOF","titulo":"Vl.Cr.Cofins","tipo":"N","tam":16,"dec":2,"validacao":"XFUNVldVal()"},{"campo":"C6M_DESEST","titulo":"Desc Estoque","tipo":"C","tam":100,"dec":0},{"campo":"C6M_CODCTA","titulo":"Id. Cod.Cont","tipo":"C","tam":36,"dec":0},{"campo":"C6M_CTACTB","titulo":"Cod Cta Ctb","tipo":"C","tam":60,"dec":0,"validacao":"XFUNVldCmp(\"C1O\",1)","ini_padrao":"IF(!INCLUI.AND.!EMPTY(C6M->C6M_CODCTA),POSICIONE(\"C1O\",3,xFilial(\"C1O\")+C6M->C6M_CODCTA, \"C1O_CODIGO\"),\"\")"},{"campo":"C6M_DCODCT","titulo":"Des.Conta","tipo":"C","tam":220,"dec":0,"ini_padrao":"xFunRelac()"},{"campo":"C6M_STATUS","titulo":"Status Reg.","tipo":"C","tam":1,"dec":0,"validacao":"Pertence(\" 012349\")","combo":"0=Reg.Válido;1=Reg.Inválido;2=Reg.Transmitido;3=Reg.Transmitido com inconsistência;4=Reg.Transmitido válido;9=Em Processamento"}],"indices":[{"ordem":"1","chave":"C6M_FILIAL+DTOS(C6M_PERIOD)+C6M_NATOPE","descricao":"Data Movto + Nat.Oper."},{"ordem":"2","chave":"C6M_FILIAL+C6M_NATOPE","descricao":"Nat.Oper."},{"ordem":"3","chave":"C6M_FILIAL+C6M_ID","descricao":"ID"}],"gatilhos":[{"origem":"C6M_ALQCOF","tipo":"","seq":"001","destino":"","regra":"FWFLDGET(\"C6M_VBCMES\")*(M->C6M_ALQCOF/100)"},{"origem":"C6M_ALQPIS","tipo":"X","seq":"001","destino":"","regra":"FWFLDGET(\"C6M_VBCMES\")*(M->C6M_ALQPIS/100)"},{"origem":"C6M_CODCTA","tipo":"X","seq":"001","destino":"","regra":"C1O->(C1O_CODIGO+' - '+C1O_DESCRI)"},{"origem":"C6M_CSTCOF","tipo":"X","seq":"001","destino":"","regra":"C17->(C17_CODIGO+' - '+C17_DESCRI)"},{"origem":"C6M_CSTPIS","tipo":"X","seq":"001","destino":"","regra":"C17->(C17_CODIGO+' - '+C17_DESCRI)"},{"origem":"C6M_CTACTB","tipo":"X","seq":"001","destino":"","regra":"C1O->(Alltrim(C1O_ID))"},{"origem":"C6M_CTACTB","tipo":"X","seq":"002","destino":"","regra":"C1O->(Alltrim(C1O_CODIGO)+' - '+C1O_DESCRI)"},{"origem":"C6M_ESTIMP","tipo":"X","seq":"001","destino":"","regra":"FWFLDGET(\"C6M_TOTEST\")-M->C6M_ESTIMP"},{"origem":"C6M_NATOPE","tipo":"X","seq":"001","destino":"","regra":"C11->(C11_CODIGO+' - '+C11_DESCRI)"},{"origem":"C6M_TOTEST","tipo":"X","seq":"001","destino":"","regra":"M->C6M_TOTEST-FWFLDGET(\"C6M_ESTIMP\")"},{"origem":"C6M_VBCEST","tipo":"P","seq":"001","destino":"","regra":"M->C6M_VBCEST/12"},{"origem":"C6M_VBCMES","tipo":"","seq":"001","destino":"","regra":"M->C6M_VBCMES*( FWFLDGET(\"C6M_ALQCOF\")/100)"}]}