{"tabela":"CD5","nome":"Complemento de importação","nome_eng":"Import additional info","modo":"E","arquivo":"CD5990","campos":[{"campo":"CD5_FILIAL","titulo":"Filial","tipo":"C","tam":2,"dec":0},{"campo":"CD5_DOC","titulo":"Número NF","tipo":"C","tam":9,"dec":0},{"campo":"CD5_SERIE","titulo":"Série NF","tipo":"C","tam":3,"dec":0},{"campo":"CD5_ESPEC","titulo":"Espécie NF","tipo":"C","tam":5,"dec":0},{"campo":"CD5_FORNEC","titulo":"Fornecedor","tipo":"C","tam":6,"dec":0},{"campo":"CD5_LOJA","titulo":"Código loja","tipo":"C","tam":2,"dec":0},{"campo":"CD5_TPIMP","titulo":"Tp. doc. imp","tipo":"C","tam":1,"dec":0,"validacao":"Pertence(\"01\")","combo":"0=Declaracao de importacao;1=Declaracao simplificada de importacao"},{"campo":"CD5_DOCIMP","titulo":"Doc. imp.","tipo":"C","tam":50,"dec":0},{"campo":"CD5_BSPIS","titulo":"Base PIS","tipo":"N","tam":14,"dec":2,"validacao":"Positivo()"},{"campo":"CD5_ALPIS","titulo":"Alíq. PIS","tipo":"N","tam":5,"dec":2,"validacao":"Positivo()"},{"campo":"CD5_VLPIS","titulo":"Val. PIS","tipo":"N","tam":14,"dec":2,"validacao":"Positivo()"},{"campo":"CD5_BSCOF","titulo":"Base Cofins","tipo":"N","tam":14,"dec":2,"validacao":"Positivo()"},{"campo":"CD5_ALCOF","titulo":"Alíq. Cofins","tipo":"N","tam":5,"dec":2,"validacao":"Positivo()"},{"campo":"CD5_VLCOF","titulo":"Val. Cofins","tipo":"N","tam":14,"dec":2,"validacao":"Positivo()"},{"campo":"CD5_LOCAL","titulo":"Local Serv","tipo":"C","tam":1,"dec":0,"validacao":"Pertence(\" 0/1\")","combo":"0=Executado no País;1=Executado no Exterior, cujo resultado se verifique no País"},{"campo":"CD5_DTPCOF","titulo":"Dt Pag Cofin","tipo":"D","tam":8,"dec":0},{"campo":"CD5_DTPPIS","titulo":"Dt Pag Pis","tipo":"D","tam":8,"dec":0},{"campo":"CD5_NDI","titulo":"No. da DI/DA","tipo":"C","tam":15,"dec":0},{"campo":"CD5_DTDI","titulo":"Registro DI","tipo":"D","tam":8,"dec":0},{"campo":"CD5_LOCDES","titulo":"Descr.Local","tipo":"C","tam":30,"dec":0},{"campo":"CD5_UFDES","titulo":"UF Desembara","tipo":"C","tam":2,"dec":0},{"campo":"CD5_DTDES","titulo":"Dt Desembar.","tipo":"D","tam":8,"dec":0},{"campo":"CD5_CODEXP","titulo":"Exportador","tipo":"C","tam":6,"dec":0,"validacao":"If(!(Vazio()),ExistCpo('SA2'),AllwaysTrue())"},{"campo":"CD5_NADIC","titulo":"Adicao","tipo":"C","tam":3,"dec":0},{"campo":"CD5_SQADIC","titulo":"Seq Adicao","tipo":"C","tam":3,"dec":0},{"campo":"CD5_BCIMP","titulo":"Vlr BC Impor","tipo":"N","tam":15,"dec":2,"validacao":"Positivo()","ini_padrao":"0"},{"campo":"CD5_CODFAB","titulo":"Fabricante","tipo":"C","tam":6,"dec":0,"validacao":"If(!(Vazio()),ExistCpo('SA2'),AllwaysTrue())"},{"campo":"CD5_DSPAD","titulo":"Vlr Desp.Adu","tipo":"N","tam":15,"dec":2,"validacao":"Positivo()"},{"campo":"CD5_VDESDI","titulo":"Vlr Desconto","tipo":"N","tam":15,"dec":2,"validacao":"Positivo()"},{"campo":"CD5_VLRII","titulo":"Vlr Imp.Impo","tipo":"N","tam":15,"dec":2,"validacao":"Positivo()"},{"campo":"CD5_VLRIOF","titulo":"Vlr IOF","tipo":"N","tam":15,"dec":2,"validacao":"Positivo()","ini_padrao":"0"},{"campo":"CD5_LOJFAB","titulo":"Loja Fab.","tipo":"C","tam":2,"dec":0},{"campo":"CD5_LOJEXP","titulo":"Loja Exp.","tipo":"C","tam":2,"dec":0},{"campo":"CD5_VTRANS","titulo":"Via Transp","tipo":"C","tam":2,"dec":0,"validacao":"Pertence(\"1 /2 /3 /4 /5 /6 /7 /8 /9 /10/11/12/13\")","combo":"#cBoxVTrans()"},{"campo":"CD5_VAFRMM","titulo":"Val. AFRMM","tipo":"N","tam":15,"dec":2,"validacao":"Positivo()"},{"campo":"CD5_INTERM","titulo":"Forma Import","tipo":"C","tam":1,"dec":0,"validacao":"Pertence(\" 1/2/3\")","combo":"1=Importação por conta própria;2=Importação por conta e ordem;3=Importação por encomenda"},{"campo":"CD5_CNPJAE","titulo":"CNPJ Adqui.","tipo":"C","tam":14,"dec":0,"validacao":"vazio() .OR. CGC(M->CD5_CNPJAE)"},{"campo":"CD5_UFTERC","titulo":"UF Terceiro","tipo":"C","tam":2,"dec":0,"validacao":"ExistCpo(\"SX5\",\"12\"+M->CD5_UFTERC)"},{"campo":"CD5_ACDRAW","titulo":"Ato Concesso","tipo":"C","tam":20,"dec":0},{"campo":"CD5_ITEM","titulo":"Item da Nota","tipo":"C","tam":4,"dec":0},{"campo":"CD5_SDOC","titulo":"Série Doc.","tipo":"C","tam":3,"dec":0},{"campo":"CD5_CPFAE","titulo":"CPF Adquir.","tipo":"C","tam":11,"dec":0}],"indices":[{"ordem":"1","chave":"CD5_FILIAL+CD5_DOC+CD5_SERIE+CD5_FORNEC+CD5_LOJA+CD5_DOCIMP+CD5_NADIC","descricao":"Número NF + Série NF + Fornecedor + Código loja + Doc. imp. + Adicao"},{"ordem":"2","chave":"CD5_FILIAL+CD5_DOCIMP+CD5_NADIC","descricao":"Doc. imp. + Adicao"},{"ordem":"3","chave":"CD5_FILIAL+CD5_DOC+CD5_SERIE+CD5_FORNEC+CD5_LOJA+CD5_DOCIMP+STR(CD5_ALPIS,5,2)+STR(CD5_ALCOF,5,2)+CD5_NADIC+CD5_SQADIC","descricao":"Número NF + Série NF + Fornecedor + Código loja + Doc. imp. + Alíq. PI"},{"ordem":"4","chave":"CD5_FILIAL+CD5_DOC+CD5_SERIE+CD5_FORNEC+CD5_LOJA+CD5_ITEM","descricao":"Número NF + Série NF + Fornecedor + Código loja + Item da Nota"},{"ordem":"5","chave":"CD5_FILIAL+CD5_DOC+CD5_SDOC+CD5_FORNEC+CD5_LOJA+CD5_DOCIMP+CD5_NADIC","descricao":"Número NF + Série Doc. + Fornecedor + Código loja + Doc. imp. + Adicao"},{"ordem":"6","chave":"CD5_FILIAL+CD5_DOC+CD5_SDOC+CD5_FORNEC+CD5_LOJA+CD5_DOCIMP+STR(CD5_ALPIS,5,2)+STR(CD5_ALCOF,5,2)+CD5_NADIC+CD5_SQADIC","descricao":"Número NF + Série Doc. + Fornecedor + Código loja + Doc. imp. + Alíq."},{"ordem":"7","chave":"CD5_FILIAL+CD5_DOC+CD5_SDOC+CD5_FORNEC+CD5_LOJA+CD5_ITEM","descricao":"Número NF + Série Doc. + Fornecedor + Código loja + Item da Nota"}],"gatilhos":[{"origem":"CD5_CODEXP","tipo":"P","seq":"001","destino":"","regra":"SA2->A2_LOJA"},{"origem":"CD5_CODFAB","tipo":"P","seq":"001","destino":"","regra":"SA2->A2_LOJA"}]}