{"tabela":"CGE","nome":"Cod. Rec. Inst. Financeiras","nome_eng":"Financial Inst. Income Code","modo":"C","arquivo":"CGE990","campos":[{"campo":"CGE_FILIAL","titulo":"Filial","tipo":"C","tam":2,"dec":0},{"campo":"CGE_COD","titulo":"Código","tipo":"C","tam":8,"dec":0},{"campo":"CGE_DESCR","titulo":"Descrição","tipo":"C","tam":250,"dec":0},{"campo":"CGE_DTINI","titulo":"Dt.Ini.","tipo":"D","tam":8,"dec":0},{"campo":"CGE_DTFIN","titulo":"Dt.Fin.","tipo":"D","tam":8,"dec":0}],"indices":[{"ordem":"1","chave":"CGE_FILIAL+CGE_COD+DTOS(CGE_DTINI)+DTOS(CGE_DTFIN)","descricao":"Código + Dt.Ini. + Dt.Fin."}],"relacionamentos":[{"dominio":"CGE","expressao_dom":"CGE_COD","identificador":"001","expressao_ident":""}]}