{"tabela":"CPM","nome":"Documentos Gerados Central de","nome_eng":"Documents Generated Central of","modo":"C","arquivo":"CPM990","campos":[{"campo":"CPM_FILIAL","titulo":"Filial","tipo":"C","tam":2,"dec":0},{"campo":"CPM_SUGEST","titulo":"N. Sugestão","tipo":"C","tam":10,"dec":0},{"campo":"CPM_FILABA","titulo":"Fil. Abastec","tipo":"C","tam":2,"dec":0},{"campo":"CPM_PRODUT","titulo":"Produto","tipo":"C","tam":15,"dec":0},{"campo":"CPM_NUMDOC","titulo":"Num. Doc.","tipo":"C","tam":6,"dec":0},{"campo":"CPM_TIPO","titulo":"Tipo Doc.","tipo":"C","tam":1,"dec":0,"validacao":"Pertence(\"12345\")","ini_padrao":"\"1\"","combo":"1=Solicitação de Compra;2=Pedido de Compra;3=Autorização de Entrega;4=Pedido de Venda;5=Medição de Contrato"}],"indices":[{"ordem":"1","chave":"CPM_FILIAL+CPM_SUGEST+CPM_FILABA+CPM_PRODUT+CPM_NUMDOC+CPM_TIPO","descricao":"N. Sugestão + Fil. Abastec + Produto + Num. Doc. + Tipo Doc."},{"ordem":"2","chave":"CPM_FILIAL+CPM_TIPO+CPM_NUMDOC","descricao":"Tipo Doc. + Num. Doc."}]}