{"tabela":"DYH","nome":"Blq. Pagto.Contrato Carreteiro","nome_eng":"Block Paymt. Teamster Contract","modo":"E","arquivo":"DYH990","campos":[{"campo":"DYH_FILIAL","titulo":"Filial","tipo":"C","tam":2,"dec":0},{"campo":"DYH_FILORI","titulo":"Fil.Origem","tipo":"C","tam":2,"dec":0},{"campo":"DYH_NUMCTC","titulo":"No.Contrato","tipo":"C","tam":9,"dec":0},{"campo":"DYH_SEQBLQ","titulo":"Seq.Bloqueio","tipo":"C","tam":2,"dec":0},{"campo":"DYH_DATBLQ","titulo":"Data Blq.","tipo":"D","tam":8,"dec":0},{"campo":"DYH_HORBLQ","titulo":"Hora Blq.","tipo":"C","tam":4,"dec":0},{"campo":"DYH_USRBLQ","titulo":"Usuario Blq.","tipo":"C","tam":6,"dec":0,"ini_padrao":"RETCODUSR()"},{"campo":"DYH_NOMBLQ","titulo":"Nome Usu.Blq","tipo":"C","tam":30,"dec":0,"ini_padrao":"UsrFullName(M->DYH_USRBLQ)"},{"campo":"DYH_MOTBLQ","titulo":"Motivo Blq.","tipo":"M","tam":80,"dec":0},{"campo":"DYH_DATLIB","titulo":"Data Lib.","tipo":"D","tam":8,"dec":0},{"campo":"DYH_HORLIB","titulo":"Hora Lib.","tipo":"C","tam":4,"dec":0},{"campo":"DYH_USRLIB","titulo":"Usuario Lib.","tipo":"C","tam":6,"dec":0,"ini_padrao":"RetCodUsr()"},{"campo":"DYH_NOMLIB","titulo":"Nme Usr.Lib.","tipo":"C","tam":30,"dec":0,"ini_padrao":"UsrFullName(M->DYH_USRBLQ)"},{"campo":"DYH_MOTLIB","titulo":"Motivo Lib.","tipo":"M","tam":80,"dec":0}],"indices":[{"ordem":"1","chave":"DYH_FILIAL+DYH_FILORI+DYH_NUMCTC+DYH_SEQBLQ","descricao":"Fil.Origem + No.Contrato + Seq.Bloqueio"}]}