{"tabela":"AZ1","nome":"Regras Comerciais X DOTs","nome_eng":"Business Rules x DOTs","modo":"E","arquivo":"AZ1990","campos":[{"campo":"AZ1_FILIAL","titulo":"Filial","tipo":"C","tam":2,"dec":0},{"campo":"AZ1_CODAGR","titulo":"Agrupador","tipo":"C","tam":6,"dec":0},{"campo":"AZ1_CODNIV","titulo":"Codigo Nível","tipo":"C","tam":3,"dec":0},{"campo":"AZ1_CODDOT","titulo":"Código Doc.","tipo":"C","tam":3,"dec":0},{"campo":"AZ1_DESDOT","titulo":"Modelo","tipo":"C","tam":100,"dec":0,"ini_padrao":"Posicione(\"AG1\",1,xFilial(\"AG1\")+AZ1->AZ1_CODDOT,\"AG1_DESCRI\")"}],"indices":[{"ordem":"1","chave":"AZ1_FILIAL+AZ1_CODAGR+AZ1_CODNIV+AZ1_CODDOT","descricao":"Agrupador + Codigo Nível + Código Doc."}],"gatilhos":[{"origem":"AZ1_CODDOT","tipo":"P","seq":"001","destino":"","regra":"AG1->AG1_DESCRI"}]}