{"tabela":"JAH","nome":"Curso Vigente","nome_eng":"Current Course","modo":"C","arquivo":"JAH990","campos":[{"campo":"JAH_FILIAL","titulo":"FILIAL","tipo":"C","tam":2,"dec":0},{"campo":"JAH_CURSO","titulo":"Curso","tipo":"C","tam":6,"dec":0,"validacao":"GEExistCpo(\"JAF\",M->JAH_CURSO) .And. ACNivSec(M->JAH_CURSO) .And. Aca110Preench()"},{"campo":"JAH_DCURSO","titulo":"Desc. Curso","tipo":"C","tam":30,"dec":0,"ini_padrao":"If(!Inclui,Posicione(\"JAF\",1,xFilial(\"JAF\")+JAH->JAH_CURSO+JAH->JAH_VERSAO,\"JAF_DESC\"),\"\")"},{"campo":"JAH_VERSAO","titulo":"Versao Curso","tipo":"C","tam":3,"dec":0},{"campo":"JAH_CODIGO","titulo":"Curso Vigent","tipo":"C","tam":6,"dec":0,"ini_padrao":"GetSXENum(\"JAH\",\"JAH_CODIGO\")"},{"campo":"JAH_DESC","titulo":"Desc.Curric.","tipo":"C","tam":50,"dec":0},{"campo":"JAH_CARGA","titulo":"Carga Horari","tipo":"N","tam":4,"dec":0},{"campo":"JAH_TURNO","titulo":"Turno","tipo":"C","tam":3,"dec":0,"validacao":"GEExistCpo(\"SX5\",\"F5\"+M->JAH_TURNO)"},{"campo":"JAH_DTURNO","titulo":"Desc. Turno","tipo":"C","tam":30,"dec":0,"ini_padrao":"If(!Inclui,Left(Posicione(\"SX5\",1,xFilial(\"SX5\")+\"F5\"+JAH->JAH_TURNO,\"X5_DESCRI\"),30),\"\")"},{"campo":"JAH_GRPDOC","titulo":"Cod.Grp.Doc.","tipo":"C","tam":6,"dec":0,"validacao":"GEExistCpo(\"JAK\",M->JAH_GRPDOC)"},{"campo":"JAH_DGRPDO","titulo":"Desc. Doc.","tipo":"C","tam":30,"dec":0,"ini_padrao":"If(!Inclui,Posicione(\"JAK\",1,xFilial(\"JAK\")+JAH->JAH_GRPDOC,\"JAK_DESC\"),\"\")"},{"campo":"JAH_AMG_","titulo":"Calcula AMG?","tipo":"C","tam":1,"dec":0,"validacao":"Pertence(\"12\")","ini_padrao":"\"2\"","combo":"1=Sim;2=Nao"},{"campo":"JAH_MEMO1","titulo":"Escopo","tipo":"C","tam":6,"dec":0},{"campo":"JAH_ESCOPO","titulo":"Escopo","tipo":"M","tam":80,"dec":0,"ini_padrao":"If(!Inclui,MSMM(JAH->JAH_MEMO1),\"\")"},{"campo":"JAH_TIPO","titulo":"Tipo","tipo":"C","tam":3,"dec":0,"validacao":"GEExistCpo(\"SX5\",\"FG\"+M->JAH_TIPO)","ini_padrao":"\"001\""},{"campo":"JAH_DTIPO","titulo":"Desc. Tipo","tipo":"C","tam":30,"dec":0,"ini_padrao":"If(!Inclui,Left(Posicione(\"SX5\",1,xFilial(\"SX5\")+\"FG\"+JAH->JAH_TIPO,\"X5_DESCRI\"),30),\"\")"},{"campo":"JAH_MEMO2","titulo":"Observacao","tipo":"C","tam":6,"dec":0},{"campo":"JAH_PREREQ","titulo":"Observacao","tipo":"M","tam":80,"dec":0,"ini_padrao":"If(!Inclui,MSMM(JAH->JAH_MEMO2),\"\")"},{"campo":"JAH_MEMO3","titulo":"Ato Legal","tipo":"C","tam":6,"dec":0},{"campo":"JAH_DECRET","titulo":"Ato Legal","tipo":"M","tam":80,"dec":0,"ini_padrao":"If(!Inclui,MSMM(JAH->JAH_MEMO3),\"\")"},{"campo":"JAH_TEMPOJ","titulo":"Integralizac","tipo":"N","tam":6,"dec":3},{"campo":"JAH_QTDTRA","titulo":"Qtd. Tranca","tipo":"N","tam":2,"dec":0},{"campo":"JAH_STATUS","titulo":"Status","tipo":"C","tam":1,"dec":0,"validacao":"Pertence(\"12\")","ini_padrao":"\"1\"","combo":"1=Em Aberto;2=Encerrado"},{"campo":"JAH_GRUPO","titulo":"Grupo","tipo":"C","tam":3,"dec":0,"validacao":"GEExistCpo(\"SX5\",\"FC\"+M->JAH_GRUPO)","ini_padrao":"\"001\""},{"campo":"JAH_DGRUPO","titulo":"Desc. Grupo","tipo":"C","tam":40,"dec":0,"ini_padrao":"Iif(Inclui, \" \", Tabela(\"FC\", JAH->JAH_GRUPO, .F.))"},{"campo":"JAH_UNIDAD","titulo":"Unidade","tipo":"C","tam":6,"dec":0,"validacao":"GEExistCpo(\"JA3\")"},{"campo":"JAH_DUNID","titulo":"Des. Unidade","tipo":"C","tam":30,"dec":0,"ini_padrao":"If(!Inclui,Posicione(\"JA3\",1,xFilial(\"JA3\")+JAH->JAH_UNIDAD,\"JA3_DESLOC\"),\"\")"},{"campo":"JAH_VALOR","titulo":"Valor","tipo":"C","tam":1,"dec":0,"validacao":"Pertence(\"12\")","ini_padrao":"\"1\"","combo":"1=Sim;2=Nao"},{"campo":"JAH_PRCSEL","titulo":"Proc.Seletiv","tipo":"C","tam":1,"dec":0,"ini_padrao":"\"2\"","combo":"1=Sim;2=Nao"},{"campo":"JAH_MATSEQ","titulo":"Matr.Sequenc","tipo":"C","tam":1,"dec":0,"validacao":"Pertence(\"12\")","ini_padrao":"\"1\"","combo":"1=Sim;2=Nao"},{"campo":"JAH_MAXDIS","titulo":"Max.Discipl.","tipo":"N","tam":2,"dec":0},{"campo":"JAH_CCOMIT","titulo":"Concomitante","tipo":"C","tam":1,"dec":0,"validacao":"Pertence(\"12\")","ini_padrao":"\"1\"","combo":"1=Concomitante;2=Nao Concomitante"},{"campo":"JAH_HABOBR","titulo":"Hab. Obrigat","tipo":"C","tam":1,"dec":0,"validacao":"Pertence(\"12\")","ini_padrao":"\"2\"","combo":"1=Sim;2=Nao"},{"campo":"JAH_MEMO4","titulo":"Motivo","tipo":"C","tam":6,"dec":0},{"campo":"JAH_MOTIVO","titulo":"Motivo","tipo":"M","tam":80,"dec":0},{"campo":"JAH_CODRAT","titulo":"Cod. Rateio","tipo":"C","tam":6,"dec":0,"validacao":"GEExistCPO(\"JHB\", M->JAH_CODRAT)"},{"campo":"JAH_DESRAT","titulo":"Des. Rateio","tipo":"C","tam":30,"dec":0,"ini_padrao":"IIF(INCLUI,\"\",Posicione(\"JHB\",1,xFilial(\"JHB\")+JAH->JAH_CODRAT,\"JHB_DESRAT\"))"},{"campo":"JAH_CERGRA","titulo":"Cer.Gratuito","tipo":"C","tam":1,"dec":0,"validacao":"PERTENCE(\"12\")","combo":"1=Sim;2=Nao"},{"campo":"JAH_NOMRES","titulo":"Responsavel","tipo":"C","tam":60,"dec":0},{"campo":"JAH_OUTCUR","titulo":"Curso comp.","tipo":"C","tam":6,"dec":0},{"campo":"JAH_DESOUT","titulo":"Des.CV Comp.","tipo":"C","tam":30,"dec":0,"ini_padrao":"If(!Inclui,Posicione(\"JAH\",1,xFilial(\"JAH\")+JAH->JAH_OUTCUR,\"JAH_DESC\"),\"\")"},{"campo":"JAH_TPPARC","titulo":"Parcelamento","tipo":"C","tam":1,"dec":0,"ini_padrao":"\"1\"","combo":"1=Calend.Fin.;2=Forma pagto"},{"campo":"JAH_MANCIC","titulo":"Não cíclico","tipo":"C","tam":1,"dec":0,"validacao":"Pertence(\"12\")","ini_padrao":"\"2\"","combo":"1=Sim;2=Não"},{"campo":"JAH_REGESP","titulo":"Regime Espec","tipo":"C","tam":1,"dec":0,"validacao":"Pertence(\"12\")","ini_padrao":"\"2\"","combo":"1=Sim;2=Não"},{"campo":"JAH_DIFER","titulo":"Diferimento","tipo":"C","tam":1,"dec":0,"validacao":"Pertence(\"12\")","ini_padrao":"\"2\"","combo":"1=Sim;2=Não"},{"campo":"JAH_PERDIF","titulo":"Per. Dif.","tipo":"C","tam":2,"dec":0}],"indices":[{"ordem":"1","chave":"JAH_FILIAL+JAH_CODIGO","descricao":"Curso Vigent"},{"ordem":"2","chave":"JAH_FILIAL+JAH_DESC","descricao":"Desc.Curric."},{"ordem":"3","chave":"JAH_FILIAL+JAH_GRPDOC","descricao":"Cod.Grp.Doc."},{"ordem":"4","chave":"JAH_FILIAL+JAH_CURSO+JAH_VERSAO","descricao":"Curso + Versao Curso"},{"ordem":"5","chave":"JAH_FILIAL+JAH_CODRAT","descricao":"Cod. Rateio"},{"ordem":"6","chave":"JAH_FILIAL+JAH_OUTCUR","descricao":"Curso comp."}],"gatilhos":[{"origem":"JAH_CURSO","tipo":"P","seq":"001","destino":"","regra":"JAF->JAF_DESC"},{"origem":"JAH_CURSO","tipo":"P","seq":"002","destino":"","regra":"JAF->JAF_VERSAO"},{"origem":"JAH_CURSO","tipo":"P","seq":"003","destino":"","regra":"JAF->JAF_DESC"},{"origem":"JAH_CURSO","tipo":"P","seq":"004","destino":"","regra":"JAF->JAF_CARGA"},{"origem":"JAH_GRPDOC","tipo":"P","seq":"001","destino":"","regra":"JAK->JAK_DESC"},{"origem":"JAH_GRUPO","tipo":"P","seq":"001","destino":"","regra":"Tabela(\"FC\", M->JAH_GRUPO, .F.)"},{"origem":"JAH_TIPO","tipo":"P","seq":"001","destino":"","regra":"TABELA(\"FG\",M->JAH_TIPO)"},{"origem":"JAH_TURNO","tipo":"P","seq":"001","destino":"","regra":"TABELA(\"F5\",M->JAH_TURNO)"},{"origem":"JAH_UNIDAD","tipo":"P","seq":"001","destino":"","regra":"JA3->JA3_DESLOC"}],"relacionamentos":[{"dominio":"JAH","expressao_dom":"JAH_CODIGO","identificador":"001","expressao_ident":""},{"dominio":"JAH","expressao_dom":"JAH_CODIGO","identificador":"002","expressao_ident":""},{"dominio":"JAH","expressao_dom":"JAH_CODIGO","identificador":"003","expressao_ident":""},{"dominio":"JAH","expressao_dom":"JAH_CODIGO","identificador":"004","expressao_ident":""},{"dominio":"JAH","expressao_dom":"JAH_CODIGO","identificador":"005","expressao_ident":""},{"dominio":"JAH","expressao_dom":"JAH_CODIGO","identificador":"006","expressao_ident":""},{"dominio":"JAH","expressao_dom":"JAH_CODIGO","identificador":"007","expressao_ident":""},{"dominio":"JAH","expressao_dom":"JAH_CODIGO","identificador":"008","expressao_ident":""},{"dominio":"JAH","expressao_dom":"JAH_CODIGO","identificador":"009","expressao_ident":""},{"dominio":"JAH","expressao_dom":"JAH_CODIGO","identificador":"010","expressao_ident":""},{"dominio":"JAH","expressao_dom":"JAH_CODIGO","identificador":"011","expressao_ident":""}]}