{"tabela":"SDJ","nome":"Clientes X Opcionais","nome_eng":"Customers x Options","modo":"E","arquivo":"SDJ990","campos":[{"campo":"DJ_FILIAL","titulo":"Filial","tipo":"C","tam":2,"dec":0},{"campo":"DJ_CLIENTE","titulo":"Cliente","tipo":"C","tam":6,"dec":0},{"campo":"DJ_TIENDA","titulo":"Loja","tipo":"C","tam":2,"dec":0},{"campo":"DJ_FAMILIA","titulo":"Familia","tipo":"C","tam":14,"dec":0,"validacao":"if (!empty(m->DJ_FAMILIA),(EXISTCPO(\"SB1\",M->DJ_FAMILIA,9)),.T.)"},{"campo":"DJ_DESCFA","titulo":"Desc Fam","tipo":"C","tam":50,"dec":0,"ini_padrao":"POSICIONE(\"SBP\",1,XFILIAL(\"SBP\")+SDJ->DJ_FAMILIA ,\"BP_DESCR\")"},{"campo":"DJ_GPOOPC","titulo":"Grupo Opc","tipo":"C","tam":3,"dec":0,"validacao":"if (!empty(m->DJ_GPOOPC),(EXISTCPO(\"SGA\",M->DJ_GPOOPC,1)),.T.)"},{"campo":"DJ_ITEOPC","titulo":"Item Opc","tipo":"C","tam":4,"dec":0,"validacao":"if (!empty(m->DJ_ITEOPC),(EXISTCPO(\"SGA\",oGetSDJ:ACOLS[N,nposgpo]+M->DJ_ITEOPC,1)),.T.)"},{"campo":"DJ_DESCITE","titulo":"Desc Item","tipo":"C","tam":40,"dec":0,"ini_padrao":"POSICIONE(\"SGA\",1,XFILIAL(\"SGA\")+SDJ->DJ_GPOOPC + SDJ->DJ_ITEOPC ,\"GA_DESCOPC\")"}],"indices":[{"ordem":"1","chave":"DJ_FILIAL+DJ_CLIENTE+DJ_TIENDA+DJ_FAMILIA+DJ_GPOOPC+DJ_ITEOPC","descricao":"Cliente + Loja + Familia + Grupo Opc + Item Opc"}]}