{"tabela":"RDE","nome":"Itens Participantes x Visões","nome_eng":"Participants Items x Vision","modo":"C","arquivo":"RDE990","campos":[{"campo":"RDE_FILIAL","titulo":"Filial","tipo":"C","tam":2,"dec":0},{"campo":"RDE_CODPAR","titulo":"Participante","tipo":"C","tam":6,"dec":0,"validacao":"RdeCodParVld()"},{"campo":"RDE_CODVIS","titulo":"Cod. Visao","tipo":"C","tam":6,"dec":0,"validacao":"RdeCodVisVld()"},{"campo":"RDE_DESCOD","titulo":"Desc.Visao","tipo":"C","tam":60,"dec":0,"ini_padrao":"RdeDesCodInit()"},{"campo":"RDE_ITEVIS","titulo":"Item Visao","tipo":"C","tam":6,"dec":0,"validacao":"RdeIteVisVld()"},{"campo":"RDE_DESITE","titulo":"Desc.Visao","tipo":"C","tam":60,"dec":0,"ini_padrao":"RdeDesIteInit()"},{"campo":"RDE_DATA","titulo":"Data Alterac","tipo":"D","tam":8,"dec":0,"validacao":"RdeDataVld()","ini_padrao":"RdeDataInit()"},{"campo":"RDE_STATUS","titulo":"Status","tipo":"C","tam":1,"dec":0,"validacao":"RdeStatusVld()","ini_padrao":"RdeStatusInit()","combo":"#RdeStatusBox()"},{"campo":"RDE_RESP","titulo":"Responsavel","tipo":"C","tam":1,"dec":0,"validacao":"Vazio() .or. Pertence(\"12\")","ini_padrao":"\"2\"","combo":"1=Sim;2=Nao"}],"indices":[{"ordem":"1","chave":"RDE_FILIAL+RDE_CODPAR+RDE_CODVIS+RDE_ITEVIS+DTOS(RDE_DATA)","descricao":"Participante + Cod. Visao + Item Visao + Data Alterac"},{"ordem":"2","chave":"RDE_FILIAL+RDE_CODVIS+RDE_ITEVIS+RDE_CODPAR+DTOS(RDE_DATA)","descricao":"Cod. Visao + Item Visao + Participante + Data Alterac"},{"ordem":"3","chave":"RDE_FILIAL+RDE_CODPAR+RDE_CODVIS+RDE_ITEVIS+RDE_STATUS","descricao":"Participante + Cod. Visao + Item Visao + Status"},{"ordem":"4","chave":"RDE_FILIAL+RDE_CODVIS+RDE_ITEVIS+RDE_CODPAR+RDE_STATUS","descricao":"Cod. Visao + Item Visao + Participante + Status"},{"ordem":"5","chave":"RDE_FILIAL+RDE_CODPAR+RDE_CODVIS+RDE_STATUS","descricao":"Participante + Cod. Visao + Status"},{"ordem":"6","chave":"RDE_FILIAL+RDE_CODVIS+RDE_CODPAR+RDE_STATUS","descricao":"Cod. Visao + Participante + Status"},{"ordem":"7","chave":"RDE_FILIAL+RDE_CODVIS+RDE_STATUS","descricao":"Cod. Visao + Status"},{"ordem":"8","chave":"RDE_FILIAL+RDE_CODVIS+RDE_ITEVIS+RDE_STATUS+RDE_CODPAR","descricao":"Cod. Visao + Item Visao + Status + Participante"}]}