{"tabela":"GLX","nome":"PROCEDIMENTO X DETALHE (Temp)","nome_eng":"PROCEDURE X DETAIL (Temp)","modo":"C","arquivo":"GLX990","campos":[{"campo":"GLX_FILIAL","titulo":"Filial","tipo":"C","tam":2,"dec":0},{"campo":"GLX_CODPRO","titulo":"Codigo","tipo":"C","tam":10,"dec":0},{"campo":"GLX_CODDET","titulo":"Cod. Atrib.","tipo":"C","tam":3,"dec":0},{"campo":"GLX_COMPET","titulo":"Competencia","tipo":"C","tam":6,"dec":0}],"indices":[{"ordem":"1","chave":"GLX_FILIAL+GLX_CODPRO+GLX_CODDET","descricao":"Codigo + Cod. Atrib."}]}