{"tabela":"NU9","nome":"PARTICIPAÇÃO DO CLIENTE","nome_eng":"CUSTOMER PARTICIPATION","modo":"C","arquivo":"NU9990","campos":[{"campo":"NU9_FILIAL","titulo":"Filial","tipo":"C","tam":2,"dec":0},{"campo":"NU9_COD","titulo":"Código","tipo":"C","tam":6,"dec":0,"ini_padrao":"GETSXENUM(\"NU9\",\"NU9_COD\")"},{"campo":"NU9_CCLIEN","titulo":"Cód cliente","tipo":"C","tam":6,"dec":0},{"campo":"NU9_CLOJA","titulo":"Cód loja","tipo":"C","tam":2,"dec":0},{"campo":"NU9_SIGLA","titulo":"Sigla part","tipo":"C","tam":5,"dec":0,"validacao":"Vazio().Or.(ExistCpo('RD0',FWFLDGET('NU9_SIGLA'),9).And.JURRD0('NU9DETAIL','NU9_SIGLA',JA148TPORI(),.T.))","ini_padrao":"IF(!INCLUI,POSICIONE('RD0',1,XFILIAL('RD0')+NU9->NU9_CPART,'RD0_SIGLA'),'')"},{"campo":"NU9_CPART","titulo":"Cód part","tipo":"C","tam":6,"dec":0,"validacao":"Vazio().Or.Iif(JurIsRest(),(ExistCpo('RD0',FWFLDGET('NU9_CPART'),1).And.JURRD0('NU9DETAIL','NU9_CPART','1')), .T.)"},{"campo":"NU9_DPART","titulo":"Nome part","tipo":"C","tam":50,"dec":0,"ini_padrao":"IF(!INCLUI,Posicione(\"RD0\",1,xFilial(\"RD0\")+NU9->NU9_CPART,\"RD0_NOME\"),'')"},{"campo":"NU9_CTIPO","titulo":"Cód tipo ori","tipo":"C","tam":3,"dec":0,"validacao":"Vazio().Or.(ExistCpo('NRI',M->NU9_CTIPO,1).AND.JA148VLDCP(\"NU9_CTIPO\"))"},{"campo":"NU9_DTIPO","titulo":"Desc tipo","tipo":"C","tam":100,"dec":0,"ini_padrao":"IF(!INCLUI,Posicione(\"NRI\",1,xFilial(\"NRI\")+NU9->NU9_CTIPO,\"NRI_DESC\"),'')"},{"campo":"NU9_PERC","titulo":"% Particip","tipo":"N","tam":16,"dec":4,"validacao":"FwFldGet(\"NU9_PERC\") <=100.And.Positivo()"},{"campo":"NU9_DTINI","titulo":"Data inicial","tipo":"D","tam":8,"dec":0,"ini_padrao":"JIniPdr(\"NU9_DTINI\")"},{"campo":"NU9_DTFIM","titulo":"Data fina","tipo":"D","tam":8,"dec":0}],"indices":[{"ordem":"1","chave":"NU9_FILIAL+NU9_CCLIEN+NU9_CLOJA+NU9_CPART+NU9_CTIPO","descricao":"Cód cliente + Cód loja + Cód part + Cód tipo ori"}],"gatilhos":[{"origem":"NU9_CPART","tipo":"P","seq":"001","destino":"","regra":"RD0->RD0_NOME"},{"origem":"NU9_CTIPO","tipo":"P","seq":"001","destino":"","regra":"NRI->NRI_DESC"},{"origem":"NU9_CTIPO","tipo":"P","seq":"002","destino":"","regra":"JurRetPraz(FwFldGet('NU9_CTIPO'), FwFldGet('NU9_DTINI'))"},{"origem":"NU9_DTINI","tipo":"P","seq":"001","destino":"","regra":"JurRetPraz(FwFldGet('NU9_CTIPO'), FwFldGet('NU9_DTINI'))"},{"origem":"NU9_PERC","tipo":"P","seq":"001","destino":"","regra":"J148ArPart()"},{"origem":"NU9_SIGLA","tipo":"P","seq":"001","destino":"","regra":"''"},{"origem":"NU9_SIGLA","tipo":"P","seq":"002","destino":"","regra":"\"\""},{"origem":"NU9_SIGLA","tipo":"P","seq":"003","destino":"","regra":"RD0->RD0_CODIGO"},{"origem":"NU9_SIGLA","tipo":"P","seq":"004","destino":"","regra":"RD0->RD0_NOME"}]}